chickenstats_api/__init__.py
chickenstats_api/api_client.py
chickenstats_api/api_response.py
chickenstats_api/configuration.py
chickenstats_api/exceptions.py
chickenstats_api/py.typed
chickenstats_api/rest.py
chickenstats_api/api/__init__.py
chickenstats_api/api/chicken_nhl_api.py
chickenstats_api/api/game_stats_api.py
chickenstats_api/api/lines_api.py
chickenstats_api/api/login_api.py
chickenstats_api/api/play_by_play_api.py
chickenstats_api/api/season_stats_api.py
chickenstats_api/api/stats_api.py
chickenstats_api/api/team_stats_api.py
chickenstats_api/api/users_api.py
chickenstats_api/models/__init__.py
chickenstats_api/models/http_validation_error.py
chickenstats_api/models/lines_create.py
chickenstats_api/models/lines_public.py
chickenstats_api/models/message.py
chickenstats_api/models/new_password.py
chickenstats_api/models/pbp_public.py
chickenstats_api/models/stats_create.py
chickenstats_api/models/stats_game.py
chickenstats_api/models/stats_season.py
chickenstats_api/models/team_stats_create.py
chickenstats_api/models/team_stats_public.py
chickenstats_api/models/token.py
chickenstats_api/models/update_password.py
chickenstats_api/models/user_create.py
chickenstats_api/models/user_public.py
chickenstats_api/models/user_update.py
chickenstats_api/models/user_update_me.py
chickenstats_api/models/users_public.py
chickenstats_api/models/validation_error.py
chickenstats_api/models/validation_error_loc_inner.py
chickenstats_api-0.0.1.dist-info/METADATA
chickenstats_api-0.0.1.dist-info/WHEEL
chickenstats_api-0.0.1.dist-info/top_level.txt
chickenstats_api-0.0.1.dist-info/RECORD
