Metadata-Version: 2.4
Name: chickenstats_api
Version: 0.0.1
Summary: chickenstats API
Home-page: 
Author: chicken
Author-email: chicken <chicken@chickenandstats.com>
License-Expression: MIT
Project-URL: Repository, https://github.com/chickenandstats/chickenstats-api-python
Keywords: OpenAPI,OpenAPI-Generator,chickenstats API
Requires-Python: >=3.9
Requires-Dist: urllib3<3.0.0,>=2.1.0
Requires-Dist: python-dateutil>=2.8.2
Requires-Dist: pydantic>=2
Requires-Dist: typing-extensions>=4.7.1
Dynamic: author
